continuiti/__init__.py
continuiti/benchmarks/__init__.py
continuiti/benchmarks/benchmark.py
continuiti/benchmarks/flame.py
continuiti/benchmarks/navierstokes.py
continuiti/benchmarks/sine.py
continuiti/benchmarks/run/__init__.py
continuiti/benchmarks/run/run_config.py
continuiti/benchmarks/run/runner.py
continuiti/data/__init__.py
continuiti/data/dataset.py
continuiti/data/mesh.py
continuiti/data/selfsupervised.py
continuiti/data/utility.py
continuiti/data/function/__init__.py
continuiti/data/function/function.py
continuiti/data/function/function_dataset.py
continuiti/data/function/function_set.py
continuiti/discrete/__init__.py
continuiti/discrete/box_sampler.py
continuiti/discrete/regular_grid.py
continuiti/discrete/sampler.py
continuiti/discrete/uniform.py
continuiti/networks/__init__.py
continuiti/networks/attention.py
continuiti/networks/deep_residual_network.py
continuiti/networks/fully_connected.py
continuiti/networks/multi_head_attention.py
continuiti/networks/scaled_dot_product_attention.py
continuiti/operators/__init__.py
continuiti/operators/belnet.py
continuiti/operators/cnn.py
continuiti/operators/dco.py
continuiti/operators/deeponet.py
continuiti/operators/dno.py
continuiti/operators/fno.py
continuiti/operators/fourierlayer.py
continuiti/operators/integralkernel.py
continuiti/operators/losses.py
continuiti/operators/neuraloperator.py
continuiti/operators/operator.py
continuiti/operators/shape.py
continuiti/pde/__init__.py
continuiti/pde/grad.py
continuiti/pde/physicsinformed.py
continuiti/trainer/__init__.py
continuiti/trainer/callbacks.py
continuiti/trainer/criterion.py
continuiti/trainer/device.py
continuiti/trainer/logs.py
continuiti/trainer/scheduler.py
continuiti/trainer/trainer.py
continuiti/transforms/__init__.py
continuiti/transforms/compose.py
continuiti/transforms/quantile_scaler.py
continuiti/transforms/scaling.py
continuiti/transforms/transform.py
continuiti-0.2.0.dist-info/LICENSE.txt
continuiti-0.2.0.dist-info/METADATA
continuiti-0.2.0.dist-info/WHEEL
continuiti-0.2.0.dist-info/top_level.txt
continuiti-0.2.0.dist-info/RECORD
