Metadata-Version: 2.1
Name: continuiti
Version: 0.2.0
Summary: Learning function operators with neural networks.
Author: appliedAI Institute gGmbH
Maintainer-email: Samuel Burbulla <s.burbulla@appliedai-institute.de>, Miguel de Benito Delgado <m.debenito@appliedai-institute.de>
License: GNU LESSER GENERAL PUBLIC LICENSE
Project-URL: Repository, https://github.com/aai-institute/continuiti.git
Project-URL: Documentation, https://aai-institute.github.io/continuiti/
Project-URL: Organization, https://www.appliedai-institute.de/en/
Project-URL: TransferLab, https://transferlab.ai/
Keywords: Artificial Intelligence,Machine Learning,Mathematics,Physics,Operator Learning,Physics-Informed ML,Neural Operator,DeepONet
Classifier: Development Status :: 3 - Alpha
Classifier: Programming Language :: Python
Classifier: License :: OSI Approved :: GNU Lesser General Public License v3 (LGPLv3)
Classifier: Topic :: Scientific/Engineering :: Artificial Intelligence
Classifier: Topic :: Scientific/Engineering :: Mathematics
Classifier: Topic :: Scientific/Engineering :: Physics
Requires-Python: >=3.9
License-File: LICENSE.txt
Requires-Dist: setuptools
Requires-Dist: numpy
Requires-Dist: matplotlib
Requires-Dist: scipy
Requires-Dist: pandas
Requires-Dist: torch<3.0.0,>=2.1.0
Requires-Dist: mlflow
Provides-Extra: dev
Requires-Dist: optuna<4.0.0,>=3.5.0; extra == "dev"
Requires-Dist: gmsh; extra == "dev"
Requires-Dist: deepxde; extra == "dev"
Requires-Dist: scikit-learn<=1.4.2; extra == "dev"
Requires-Dist: black; extra == "dev"
Requires-Dist: flake8; extra == "dev"
Requires-Dist: isort; extra == "dev"
Requires-Dist: pre-commit; extra == "dev"
Requires-Dist: pudb; extra == "dev"
Requires-Dist: pytest; extra == "dev"
Requires-Dist: pytest-cov; extra == "dev"
Requires-Dist: nbmake; extra == "dev"
Requires-Dist: markdown-captions; extra == "dev"
Requires-Dist: mike; extra == "dev"
Requires-Dist: mkdocs==1.5.2; extra == "dev"
Requires-Dist: mkdocs-alias-plugin>=0.6.0; extra == "dev"
Requires-Dist: mkdocs-autorefs; extra == "dev"
Requires-Dist: mkdocs-gen-files; extra == "dev"
Requires-Dist: mkdocs-git-revision-date-localized-plugin; extra == "dev"
Requires-Dist: mkdocs-glightbox; extra == "dev"
Requires-Dist: mkdocs-literate-nav; extra == "dev"
Requires-Dist: mkdocs-macros-plugin; extra == "dev"
Requires-Dist: mkdocs-material; extra == "dev"
Requires-Dist: mkdocs-section-index; extra == "dev"
Requires-Dist: mkdocstrings[python]>=0.18; extra == "dev"
Requires-Dist: mknotebooks>=0.8.0; extra == "dev"
Requires-Dist: neoteroi-mkdocs; extra == "dev"
Requires-Dist: pygments; extra == "dev"
Requires-Dist: bump-my-version; extra == "dev"
